.gitignore
MANIFEST
README.md
requirements.txt
setup.cfg
setup.py
.github/ISSUE_TEMPLATE/bug-template.md
.github/ISSUE_TEMPLATE/classification-results-issue.md
.github/ISSUE_TEMPLATE/feature_request.md
ftr_classifier/__build_lemmatizer.py
ftr_classifier/__init__.py
ftr_classifier/classify.py
ftr_classifier/info.py
ftr_classifier/lemma_count.py
ftr_classifier/manage_functions.py
ftr_classifier/models.py
ftr_classifier/word_lists.py
ftr_classifier.egg-info/PKG-INFO
ftr_classifier.egg-info/SOURCES.txt
ftr_classifier.egg-info/dependency_links.txt
ftr_classifier.egg-info/requires.txt
ftr_classifier.egg-info/top_level.txt
ftr_classifier/data/bibtex.bib
ftr_classifier/data/lemma_map
ftr_classifier/data/meta_data
minimal_examples/minimal_example.ipynb
minimal_examples/minimal_example.py
minimal_examples/toy_data/example.pkl