Metadata-Version: 1.2
Name: ftr-classifier
Version: 1.2.16
Summary: Classifies English, Dutch and German sentences in terms of how they refer to the future.
Home-page: https://github.com/cbjrobertson/ftr_classifier.git
Author: cole robertson
Author-email: cbjrobertson@gmail.com
License: MIT
Download-URL: https://github.com/cbjrobertson/future_modality/archive/1.2.16.tar.gz
Platform: UNKNOWN
Requires-Python: ==3.6.*
